imageTest2020/__init__.py
imageTest2020/imageTest2020.py
imageTest2020-0.0.8.dist-info/METADATA
imageTest2020-0.0.8.dist-info/WHEEL
imageTest2020-0.0.8.dist-info/top_level.txt
imageTest2020-0.0.8.dist-info/RECORD
