Metadata-Version: 2.1
Name: imageTest2020
Version: 0.0.8
Summary: string to date
Home-page: UNKNOWN
Author: zxw
Author-email: 761479698@qq.com
License: MIT
Platform: UNKNOWN
